[[1.034708,{"lines":{"0":[["                                                                                                                                                                         ",{}]],"1":[["                                                                                                                                                                         ",{}]],"2":[["                                                                                                                                                                         ",{}]],"3":[["                                                                                                                                                                         ",{}]],"4":[["                                                                                                                                                                         ",{}]],"5":[["                                                                                                                                                                         ",{}]],"6":[["                                                                                                                                                                         ",{}]],"7":[["                                                                                                                                                                         ",{}]],"8":[["                                                                                                                                                                         ",{}]],"9":[["                                                                                                                                                                         ",{}]]},"cursor":{"x":0,"y":0,"visible":true}}],[0.002406,{"lines":{"0":[["honeycookie:~#                                                                                                                                                           ",{}]]},"cursor":{"x":15}}],[1.688927,{"lines":{"0":[["honeycookie:~# l                                                                                                                                                         ",{}]]},"cursor":{"x":16}}],[0.096771,{"lines":{"0":[["honeycookie:~# ls                                                                                                                                                        ",{}]]},"cursor":{"x":17}}],[0.120292,{"cursor":{"x":0,"y":1}}],[0.005195,{"lines":{"1":[["honeycookie:~#                                                                                                                                                           ",{}]]},"cursor":{"x":15}}],[0.686248,{"lines":{"1":[["honeycookie:~# p                                                                                                                                                         ",{}]]},"cursor":{"x":16}}],[0.047538,{"lines":{"1":[["honeycookie:~# pw                                                                                                                                                        ",{}]]},"cursor":{"x":17}}],[0.137044,{"lines":{"1":[["honeycookie:~# pwd                                                                                                                                                       ",{}]]},"cursor":{"x":18}}],[0.120048,{"cursor":{"x":0,"y":2}}],[0.005697,{"lines":{"2":[["/root                                                                                                                                                                    ",{}]],"3":[["honeycookie:~#                                                                                                                                                           ",{}]]},"cursor":{"x":15,"y":3}}],[2.562138,{"lines":{"3":[["honeycookie:~# y                                                                                                                                                         ",{}]]},"cursor":{"x":16}}],[0.165739,{"lines":{"3":[["honeycookie:~# ya                                                                                                                                                        ",{}]]},"cursor":{"x":17}}],[0.097344,{"lines":{"3":[["honeycookie:~# yao                                                                                                                                                       ",{}]]},"cursor":{"x":18}}],[0.124332,{"lines":{"3":[["honeycookie:~# yaou                                                                                                                                                      ",{}]]},"cursor":{"x":19}}],[0.043924,{"lines":{"3":[["honeycookie:~# yaour                                                                                                                                                     ",{}]]},"cursor":{"x":20}}],[0.256262,{"lines":{"3":[["honeycookie:~# yaourt                                                                                                                                                    ",{}]]},"cursor":{"x":21}}],[0.193828,{"cursor":{"x":0,"y":4}}],[0.004361,{"lines":{"4":[["bash: yaourt: command not found                                                                                                                                          ",{}]],"5":[["honeycookie:~#                                                                                                                                                           ",{}]]},"cursor":{"x":15,"y":5}}],[0.679888,{"lines":{"5":[["honeycookie:~# y                                                                                                                                                         ",{}]]},"cursor":{"x":16}}],[0.478518,{"cursor":{"x":15}}],[0.000478,{"lines":{"5":[["honeycookie:~#                                                                                                                                                           ",{}]]}}],[1.02494,{}],[0.002309,{"lines":{"0":[["Connection to server closed.                                                                                                                                             ",{}]],"1":[["localhost:~#                                                                                                                                                             ",{}]],"2":[["                                                                                                                                                                         ",{}]],"3":[["                                                                                                                                                                         ",{}]],"4":[["                                                                                                                                                                         ",{}]],"5":[["                                                                                                                                                                         ",{}]]},"cursor":{"x":13,"y":1}}],[3.003089,{}],[0.002387,{}],[0.80757,{}],[0.002176,{}],[0.376381,{}],[0.00265,{}],[0.238675,{}],[0.002806,{}],[0.181801,{}],[0.00297,{}],[0.308695,{"lines":{"1":[["localhost:~# e                                                                                                                                                           ",{}]]},"cursor":{"x":14}}],[0.267584,{"lines":{"1":[["localhost:~# ex                                                                                                                                                          ",{}]]},"cursor":{"x":15}}],[0.112359,{"lines":{"1":[["localhost:~# exi                                                                                                                                                         ",{}]]},"cursor":{"x":16}}],[0.093802,{"lines":{"1":[["localhost:~# exit                                                                                                                                                        ",{}]]},"cursor":{"x":17}}],[0.144677,{"cursor":{"x":0,"y":2}}],[0.00403,{"lines":{"1":[["localhost:~#                                                                                                                                                             ",{}]]},"cursor":{"x":13,"y":1}}],[0.590062,{"lines":{"1":[["localhost:~# e                                                                                                                                                           ",{}]]},"cursor":{"x":14}}],[0.191562,{"lines":{"1":[["localhost:~# ex                                                                                                                                                          ",{}]]},"cursor":{"x":15}}],[0.072092,{"lines":{"1":[["localhost:~# exi                                                                                                                                                         ",{}]]},"cursor":{"x":16}}],[0.146108,{"lines":{"1":[["localhost:~# exit                                                                                                                                                        ",{}]]},"cursor":{"x":17}}],[0.087543,{"cursor":{"x":0,"y":2}}],[0.003654,{"lines":{"1":[["localhost:~#                                                                                                                                                             ",{}]]},"cursor":{"x":13,"y":1}}],[0.164244,{"lines":{"1":[["localhost:~# e                                                                                                                                                           ",{}]]},"cursor":{"x":14}}],[0.168295,{"lines":{"1":[["localhost:~# ei                                                                                                                                                          ",{}]]},"cursor":{"x":15}}],[0.097495,{"lines":{"1":[["localhost:~# eix                                                                                                                                                         ",{}]]},"cursor":{"x":16}}],[0.495984,{"cursor":{"x":15}}],[0.000446,{"lines":{"1":[["localhost:~# ei                                                                                                                                                          ",{}]]}}],[0.191544,{"cursor":{"x":14}}],[0.00044,{"lines":{"1":[["localhost:~# e                                                                                                                                                           ",{}]]}}],[0.09633899999999999,{"lines":{"1":[["localhost:~# ex                                                                                                                                                          ",{}]]},"cursor":{"x":15}}],[0.121662,{"lines":{"1":[["localhost:~# exi                                                                                                                                                         ",{}]]},"cursor":{"x":16}}],[0.22167,{"lines":{"1":[["localhost:~# exit                                                                                                                                                        ",{}]]},"cursor":{"x":17}}],[0.082744,{"cursor":{"x":0,"y":2}}],[0.003787,{"lines":{"1":[["localhost:~#                                                                                                                                                             ",{}]]},"cursor":{"x":13,"y":1}}],[0.050827,{"lines":{"1":[["localhost:~# e                                                                                                                                                           ",{}]]},"cursor":{"x":14}}],[0.322694,{"lines":{"1":[["localhost:~# ex                                                                                                                                                          ",{}]]},"cursor":{"x":15}}],[0.143954,{"lines":{"1":[["localhost:~# exi                                                                                                                                                         ",{}]]},"cursor":{"x":16}}],[0.143897,{"lines":{"1":[["localhost:~# exit                                                                                                                                                        ",{}]]},"cursor":{"x":17}}],[0.119974,{"cursor":{"x":0,"y":2}}],[0.004113,{"lines":{"1":[["localhost:~#                                                                                                                                                             ",{}]]},"cursor":{"x":13,"y":1}}],[0.143271,{"lines":{"1":[["localhost:~# e                                                                                                                                                           ",{}]]},"cursor":{"x":14}}],[0.206299,{"lines":{"1":[["localhost:~# ex                                                                                                                                                          ",{}]]},"cursor":{"x":15}}],[0.12737,{"lines":{"1":[["localhost:~# exi                                                                                                                                                         ",{}]]},"cursor":{"x":16}}],[0.113337,{"lines":{"1":[["localhost:~# exit                                                                                                                                                        ",{}]]},"cursor":{"x":17}}],[0.096956,{"cursor":{"x":0,"y":2}}],[0.003941,{"lines":{"1":[["localhost:~#                                                                                                                                                             ",{}]]},"cursor":{"x":13,"y":1}}],[0.122824,{"lines":{"1":[["localhost:~# e                                                                                                                                                           ",{}]]},"cursor":{"x":14}}],[0.227838,{"lines":{"1":[["localhost:~# ex                                                                                                                                                          ",{}]]},"cursor":{"x":15}}],[0.09607499999999999,{"lines":{"1":[["localhost:~# exi                                                                                                                                                         ",{}]]},"cursor":{"x":16}}],[0.119944,{"lines":{"1":[["localhost:~# exit                                                                                                                                                        ",{}]]},"cursor":{"x":17}}],[0.193618,{"cursor":{"x":0,"y":2}}],[0.004210999999999999,{"lines":{"1":[["localhost:~#                                                                                                                                                             ",{}]]},"cursor":{"x":13,"y":1}}],[0.044398,{"lines":{"1":[["localhost:~# e                                                                                                                                                           ",{}]]},"cursor":{"x":14}}],[0.255997,{"lines":{"1":[["localhost:~# ex                                                                                                                                                          ",{}]]},"cursor":{"x":15}}],[0.119621,{"lines":{"1":[["localhost:~# exi                                                                                                                                                         ",{}]]},"cursor":{"x":16}}],[0.14193,{"lines":{"1":[["localhost:~# exit                                                                                                                                                        ",{}]]},"cursor":{"x":17}}],[0.123742,{"cursor":{"x":0,"y":2}}],[0.003561,{"lines":{"1":[["localhost:~#                                                                                                                                                             ",{}]]},"cursor":{"x":13,"y":1}}],[0.141505,{"lines":{"1":[["localhost:~# e                                                                                                                                                           ",{}]]},"cursor":{"x":14}}],[0.208765,{"lines":{"1":[["localhost:~# ex                                                                                                                                                          ",{}]]},"cursor":{"x":15}}],[0.118833,{"lines":{"1":[["localhost:~# exi                                                                                                                                                         ",{}]]},"cursor":{"x":16}}],[0.144729,{"lines":{"1":[["localhost:~# exit                                                                                                                                                        ",{}]]},"cursor":{"x":17}}],[0.144369,{"cursor":{"x":0,"y":2}}],[0.003946,{"lines":{"1":[["localhost:~#                                                                                                                                                             ",{}]]},"cursor":{"x":13,"y":1}}],[0.108802,{"lines":{"1":[["localhost:~# e                                                                                                                                                           ",{}]]},"cursor":{"x":14}}],[0.218091,{"lines":{"1":[["localhost:~# ex                                                                                                                                                          ",{}]]},"cursor":{"x":15}}],[0.119139,{"lines":{"1":[["localhost:~# exi                                                                                                                                                         ",{}]]},"cursor":{"x":16}}],[0.169037,{"lines":{"1":[["localhost:~# exit                                                                                                                                                        ",{}]]},"cursor":{"x":17}}],[0.134753,{"cursor":{"x":0,"y":2}}],[0.003966,{"lines":{"1":[["localhost:~#                                                                                                                                                             ",{}]]},"cursor":{"x":13,"y":1}}],[0.09446599999999999,{"lines":{"1":[["localhost:~# e                                                                                                                                                           ",{}]]},"cursor":{"x":14}}],[0.215111,{"lines":{"1":[["localhost:~# ex                                                                                                                                                          ",{}]]},"cursor":{"x":15}}],[0.333572,{"lines":{"1":[["localhost:~# exi                                                                                                                                                         ",{}]]},"cursor":{"x":16}}],[0.001511,{"lines":{"1":[["localhost:~# exit                                                                                                                                                        ",{}]]},"cursor":{"x":17}}],[0.139493,{"cursor":{"x":0,"y":2}}],[0.004900000000000001,{"lines":{"1":[["localhost:~#                                                                                                                                                             ",{}]]},"cursor":{"x":13,"y":1}}],[0.236962,{"lines":{"1":[["localhost:~# e                                                                                                                                                           ",{}]]},"cursor":{"x":14}}],[0.712585,{"cursor":{"x":13}}],[0.000351,{"lines":{"1":[["localhost:~#                                                                                                                                                             ",{}]]}}],[0.856916,{"lines":{"1":[["localhost:~# w                                                                                                                                                           ",{}]]},"cursor":{"x":14}}],[0.096008,{"lines":{"1":[["localhost:~# wh                                                                                                                                                          ",{}]]},"cursor":{"x":15}}],[0.063012,{"lines":{"1":[["localhost:~# whi                                                                                                                                                         ",{}]]},"cursor":{"x":16}}],[0.100471,{"lines":{"1":[["localhost:~# whil                                                                                                                                                        ",{}]]},"cursor":{"x":17}}],[0.09321,{"lines":{"1":[["localhost:~# while                                                                                                                                                       ",{}]]},"cursor":{"x":18}}],[0.119545,{"cursor":{"x":19}}],[0.12142,{"lines":{"1":[["localhost:~# while t                                                                                                                                                     ",{}]]},"cursor":{"x":20}}],[0.215963,{"lines":{"1":[["localhost:~# while tr                                                                                                                                                    ",{}]]},"cursor":{"x":21}}],[0.112123,{"lines":{"1":[["localhost:~# while tru                                                                                                                                                   ",{}]]},"cursor":{"x":22}}],[0.191858,{"lines":{"1":[["localhost:~# while true                                                                                                                                                  ",{}]]},"cursor":{"x":23}}],[0.240973,{"lines":{"1":[["localhost:~# while true;                                                                                                                                                 ",{}]]},"cursor":{"x":24}}],[0.2085,{"cursor":{"x":25}}],[0.168679,{"lines":{"1":[["localhost:~# while true; e                                                                                                                                               ",{}]]},"cursor":{"x":26}}],[0.263666,{"lines":{"1":[["localhost:~# while true; ex                                                                                                                                              ",{}]]},"cursor":{"x":27}}],[0.233172,{"lines":{"1":[["localhost:~# while true; exi                                                                                                                                             ",{}]]},"cursor":{"x":28}}],[0.168636,{"lines":{"1":[["localhost:~# while true; exit                                                                                                                                            ",{}]]},"cursor":{"x":29}}],[0.313366,{"lines":{"1":[["localhost:~# while true; exit;                                                                                                                                           ",{}]]},"cursor":{"x":30}}],[0.738459,{"cursor":{"x":29}}],[0.00034,{"lines":{"1":[["localhost:~# while true; exit                                                                                                                                            ",{}]]}}],[0.142178,{"cursor":{"x":28}}],[0.000458,{"lines":{"1":[["localhost:~# while true; exi                                                                                                                                             ",{}]]}}],[0.207328,{"cursor":{"x":27}}],[0.000576,{"lines":{"1":[["localhost:~# while true; ex                                                                                                                                              ",{}]]}}],[0.216877,{"cursor":{"x":26}}],[0.000566,{"lines":{"1":[["localhost:~# while true; e                                                                                                                                               ",{}]]}}],[0.219893,{"cursor":{"x":25}}],[0.000437,{"lines":{"1":[["localhost:~# while true;                                                                                                                                                 ",{}]]}}],[0.323944,{"lines":{"1":[["localhost:~# while true; d                                                                                                                                               ",{}]]},"cursor":{"x":26}}],[0.168872,{"lines":{"1":[["localhost:~# while true; do                                                                                                                                              ",{}]]},"cursor":{"x":27}}],[0.280518,{"lines":{"1":[["localhost:~# while true; do;                                                                                                                                             ",{}]]},"cursor":{"x":28}}],[0.215974,{"cursor":{"x":29}}],[0.119386,{"lines":{"1":[["localhost:~# while true; do; e                                                                                                                                           ",{}]]},"cursor":{"x":30}}],[0.265843,{"lines":{"1":[["localhost:~# while true; do; ex                                                                                                                                          ",{}]]},"cursor":{"x":31}}],[0.134166,{"lines":{"1":[["localhost:~# while true; do; exi                                                                                                                                         ",{}]]},"cursor":{"x":32}}],[0.146462,{"lines":{"1":[["localhost:~# while true; do; exit                                                                                                                                        ",{}]]},"cursor":{"x":33}}],[0.31119,{"lines":{"1":[["localhost:~# while true; do; exit;                                                                                                                                       ",{}]]},"cursor":{"x":34}}],[0.305027,{"cursor":{"x":35}}],[0.16896,{"lines":{"1":[["localhost:~# while true; do; exit; e                                                                                                                                     ",{}]]},"cursor":{"x":36}}],[0.143798,{"lines":{"1":[["localhost:~# while true; do; exit; en                                                                                                                                    ",{}]]},"cursor":{"x":37}}],[0.169027,{"lines":{"1":[["localhost:~# while true; do; exit; end                                                                                                                                   ",{}]]},"cursor":{"x":38}}],[0.183613,{"cursor":{"x":0,"y":2}}],[0.008966,{"lines":{"1":[["bash: end: command not found                                                                                                                                             ",{}]],"2":[["localhost:~#                                                                                                                                                             ",{}]]},"cursor":{"x":13}}],[3.003047,{"lines":{"2":[["localhost:~# w                                                                                                                                                           ",{}]]},"cursor":{"x":14}}],[0.095752,{"lines":{"2":[["localhost:~# wh                                                                                                                                                          ",{}]]},"cursor":{"x":15}}],[0.088175,{"lines":{"2":[["localhost:~# whi                                                                                                                                                         ",{}]]},"cursor":{"x":16}}],[0.09782399999999999,{"lines":{"2":[["localhost:~# whil                                                                                                                                                        ",{}]]},"cursor":{"x":17}}],[0.072895,{"lines":{"2":[["localhost:~# while                                                                                                                                                       ",{}]]},"cursor":{"x":18}}],[0.094608,{"cursor":{"x":19}}],[0.375408,{"cursor":{"x":18}}],[0.000387,{}],[0.661357,{"cursor":{"x":17}}],[0.00044,{"lines":{"2":[["localhost:~# whil                                                                                                                                                        ",{}]]}}],[0.038961,{"cursor":{"x":16}}],[0.000387,{"lines":{"2":[["localhost:~# whi                                                                                                                                                         ",{}]]}}],[0.041919,{"cursor":{"x":15}}],[0.000337,{"lines":{"2":[["localhost:~# wh                                                                                                                                                          ",{}]]}}],[0.040342,{"cursor":{"x":14}}],[0.000569,{"lines":{"2":[["localhost:~# w                                                                                                                                                           ",{}]]}}],[0.043183,{"cursor":{"x":13}}],[0.000569,{"lines":{"2":[["localhost:~#                                                                                                                                                             ",{}]]}}],[0.79201,{"lines":{"2":[["localhost:~# e                                                                                                                                                           ",{}]]},"cursor":{"x":14}}],[0.241081,{"lines":{"2":[["localhost:~# ec                                                                                                                                                          ",{}]]},"cursor":{"x":15}}],[0.072034,{"lines":{"2":[["localhost:~# ech                                                                                                                                                         ",{}]]},"cursor":{"x":16}}],[0.087545,{"lines":{"2":[["localhost:~# echo                                                                                                                                                        ",{}]]},"cursor":{"x":17}}],[0.071927,{"cursor":{"x":18}}],[0.690078,{"lines":{"2":[["localhost:~# echo $                                                                                                                                                      ",{}]]},"cursor":{"x":19}}],[0.5512049999999999,{"cursor":{"x":18}}],[0.000456,{"lines":{"2":[["localhost:~# echo                                                                                                                                                        ",{}]]}}],[0.352319,{"lines":{"2":[["localhost:~# echo \"                                                                                                                                                      ",{}]]},"cursor":{"x":19}}],[0.8995880000000001,{"lines":{"2":[["localhost:~# echo \"b                                                                                                                                                     ",{}]]},"cursor":{"x":20}}],[0.031296,{"lines":{"2":[["localhost:~# echo \"bo                                                                                                                                                    ",{}]]},"cursor":{"x":21}}],[0.09433,{"lines":{"2":[["localhost:~# echo \"bor                                                                                                                                                   ",{}]]},"cursor":{"x":22}}],[0.049607,{"lines":{"2":[["localhost:~# echo \"bore                                                                                                                                                  ",{}]]},"cursor":{"x":23}}],[0.255927,{"lines":{"2":[["localhost:~# echo \"bored                                                                                                                                                 ",{}]]},"cursor":{"x":24}}],[0.265622,{"lines":{"2":[["localhost:~# echo \"bored\"                                                                                                                                                ",{}]]},"cursor":{"x":25}}],[0.206787,{"cursor":{"x":0,"y":3}}],[0.004218,{"lines":{"3":[["bored                                                                                                                                                                    ",{}]],"4":[["localhost:~#                                                                                                                                                             ",{}]]},"cursor":{"x":13,"y":4}}],[0.758275,{"lines":{"4":[["localhost:~# w                                                                                                                                                           ",{}]]},"cursor":{"x":14}}],[0.096569,{"lines":{"4":[["localhost:~# wh                                                                                                                                                          ",{}]]},"cursor":{"x":15}}],[0.047739,{"lines":{"4":[["localhost:~# whi                                                                                                                                                         ",{}]]},"cursor":{"x":16}}],[0.096999,{"lines":{"4":[["localhost:~# whil                                                                                                                                                        ",{}]]},"cursor":{"x":17}}],[0.07212499999999999,{"lines":{"4":[["localhost:~# while                                                                                                                                                       ",{}]]},"cursor":{"x":18}}],[0.09497999999999999,{"cursor":{"x":19}}],[0.280899,{"lines":{"4":[["localhost:~# while t                                                                                                                                                     ",{}]]},"cursor":{"x":20}}],[0.215538,{"lines":{"4":[["localhost:~# while tr                                                                                                                                                    ",{}]]},"cursor":{"x":21}}],[0.121102,{"lines":{"4":[["localhost:~# while tru                                                                                                                                                   ",{}]]},"cursor":{"x":22}}],[0.353021,{"lines":{"4":[["localhost:~# while true                                                                                                                                                  ",{}]]},"cursor":{"x":23}}],[0.3603,{"lines":{"4":[["localhost:~# while true;                                                                                                                                                 ",{}]]},"cursor":{"x":24}}],[0.216626,{"cursor":{"x":25}}],[0.111337,{"lines":{"4":[["localhost:~# while true; e                                                                                                                                               ",{}]]},"cursor":{"x":26}}],[0.288832,{"lines":{"4":[["localhost:~# while true; ec                                                                                                                                              ",{}]]},"cursor":{"x":27}}],[0.263365,{"lines":{"4":[["localhost:~# while true; ech                                                                                                                                             ",{}]]},"cursor":{"x":28}}],[0.028193,{"lines":{"4":[["localhost:~# while true; echo                                                                                                                                            ",{}]]},"cursor":{"x":29}}],[0.182486,{"cursor":{"x":30}}],[1.37787,{"lines":{"4":[["localhost:~# while true; echo \"                                                                                                                                          ",{}]]},"cursor":{"x":31}}],[1.737654,{"lines":{"4":[["localhost:~# while true; echo \"I                                                                                                                                         ",{}]]},"cursor":{"x":32}}],[0.209027,{"lines":{"4":[["localhost:~# while true; echo \"I'                                                                                                                                        ",{}]]},"cursor":{"x":33}}],[0.264723,{"lines":{"4":[["localhost:~# while true; echo \"I'm                                                                                                                                       ",{}]]},"cursor":{"x":34}}],[0.11979,{"cursor":{"x":35}}],[0.144176,{"lines":{"4":[["localhost:~# while true; echo \"I'm b                                                                                                                                     ",{}]]},"cursor":{"x":36}}],[0.094581,{"lines":{"4":[["localhost:~# while true; echo \"I'm bo                                                                                                                                    ",{}]]},"cursor":{"x":37}}],[0.136673,{"lines":{"4":[["localhost:~# while true; echo \"I'm bor                                                                                                                                   ",{}]]},"cursor":{"x":38}}],[0.072162,{"lines":{"4":[["localhost:~# while true; echo \"I'm bore                                                                                                                                  ",{}]]},"cursor":{"x":39}}],[0.241059,{"lines":{"4":[["localhost:~# while true; echo \"I'm bored                                                                                                                                 ",{}]]},"cursor":{"x":40}}],[0.232718,{"lines":{"4":[["localhost:~# while true; echo \"I'm bored.                                                                                                                                ",{}]]},"cursor":{"x":41}}],[0.47993,{"lines":{"4":[["localhost:~# while true; echo \"I'm bored.\"                                                                                                                               ",{}]]},"cursor":{"x":42}}],[0.858258,{"cursor":{"x":41}}],[0.00042,{"lines":{"4":[["localhost:~# while true; echo \"I'm bored.                                                                                                                                ",{}]]}}],[0.776882,{"cursor":{"x":40}}],[0.005337000000000001,{"lines":{"4":[["localhost:~# while true; echo \"I'm bo                                                                                                                                    ",{}]]},"cursor":{"x":37}}],[0.057385,{"cursor":{"x":36}}],[0.0009700000000000001,{"lines":{"4":[["localhost:~# while true; echo \"I'm b                                                                                                                                     ",{}]]}}],[0.021669,{"cursor":{"x":35}}],[0.000466,{"lines":{"4":[["localhost:~# while true; echo \"I'm                                                                                                                                       ",{}]]}}],[0.041392,{"cursor":{"x":34}}],[0.000476,{}],[0.039905,{"cursor":{"x":33}}],[0.000401,{"lines":{"4":[["localhost:~# while true; echo \"I'                                                                                                                                        ",{}]]}}],[0.041796,{"cursor":{"x":32}}],[0.000304,{"lines":{"4":[["localhost:~# while true; echo \"I                                                                                                                                         ",{}]]}}],[0.039352,{"cursor":{"x":31}}],[0.000414,{"lines":{"4":[["localhost:~# while true; echo \"                                                                                                                                          ",{}]]}}],[0.040113,{"cursor":{"x":30}}],[0.000372,{"lines":{"4":[["localhost:~# while true; echo                                                                                                                                            ",{}]]}}],[0.039361,{"cursor":{"x":29}}],[0.000363,{}],[0.042224,{"cursor":{"x":28}}],[0.000366,{"lines":{"4":[["localhost:~# while true; ech                                                                                                                                             ",{}]]}}],[0.466054,{"cursor":{"x":27}}],[0.000289,{"lines":{"4":[["localhost:~# while true; ec                                                                                                                                              ",{}]]}}],[0.238353,{"cursor":{"x":26}}],[0.000235,{"lines":{"4":[["localhost:~# while true; e                                                                                                                                               ",{}]]}}],[0.208164,{"cursor":{"x":25}}],[0.000354,{"lines":{"4":[["localhost:~# while true;                                                                                                                                                 ",{}]]}}],[0.2887,{"lines":{"4":[["localhost:~# while true; d                                                                                                                                               ",{}]]},"cursor":{"x":26}}],[0.1191,{"lines":{"4":[["localhost:~# while true; do                                                                                                                                              ",{}]]},"cursor":{"x":27}}],[0.267285,{"cursor":{"x":28}}],[0.327887,{"cursor":{"x":27}}],[0.000379,{}],[0.35032,{"lines":{"4":[["localhost:~# while true; do;                                                                                                                                             ",{}]]},"cursor":{"x":28}}],[0.144567,{"cursor":{"x":29}}],[0.096801,{"lines":{"4":[["localhost:~# while true; do; e                                                                                                                                           ",{}]]},"cursor":{"x":30}}],[0.263317,{"lines":{"4":[["localhost:~# while true; do; ec                                                                                                                                          ",{}]]},"cursor":{"x":31}}],[0.077723,{"lines":{"4":[["localhost:~# while true; do; ech                                                                                                                                         ",{}]]},"cursor":{"x":32}}],[0.090851,{"lines":{"4":[["localhost:~# while true; do; echo                                                                                                                                        ",{}]]},"cursor":{"x":33}}],[0.112311,{"cursor":{"x":34}}],[1.218796,{"lines":{"4":[["localhost:~# while true; do; echo \"                                                                                                                                      ",{}]]},"cursor":{"x":35}}],[0.562488,{"lines":{"4":[["localhost:~# while true; do; echo \"I                                                                                                                                     ",{}]]},"cursor":{"x":36}}],[0.108709,{"lines":{"4":[["localhost:~# while true; do; echo \"I'                                                                                                                                    ",{}]]},"cursor":{"x":37}}],[0.250496,{"lines":{"4":[["localhost:~# while true; do; echo \"I'm                                                                                                                                   ",{}]]},"cursor":{"x":38}}],[0.122662,{"cursor":{"x":39}}],[0.165182,{"lines":{"4":[["localhost:~# while true; do; echo \"I'm b                                                                                                                                 ",{}]]},"cursor":{"x":40}}],[0.071732,{"lines":{"4":[["localhost:~# while true; do; echo \"I'm bo                                                                                                                                ",{}]]},"cursor":{"x":41}}],[0.159607,{"lines":{"4":[["localhost:~# while true; do; echo \"I'm bor                                                                                                                               ",{}]]},"cursor":{"x":42}}],[0.049513,{"lines":{"4":[["localhost:~# while true; do; echo \"I'm bore                                                                                                                              ",{}]]},"cursor":{"x":43}}],[0.262778,{"lines":{"4":[["localhost:~# while true; do; echo \"I'm bored                                                                                                                             ",{}]]},"cursor":{"x":44}}],[0.144796,{"lines":{"4":[["localhost:~# while true; do; echo \"I'm bored.                                                                                                                            ",{}]]},"cursor":{"x":45}}],[0.921607,{"cursor":{"x":44}}],[0.000364,{"lines":{"4":[["localhost:~# while true; do; echo \"I'm bored                                                                                                                             ",{}]]}}],[0.289728,{"lines":{"4":[["localhost:~# while true; do; echo \"I'm bored!                                                                                                                            ",{}]]},"cursor":{"x":45}}],[0.376771,{"lines":{"4":[["localhost:~# while true; do; echo \"I'm bored!\"                                                                                                                           ",{}]]},"cursor":{"x":46}}],[0.5991919999999999,{"lines":{"4":[["localhost:~# while true; do; echo \"I'm bored!\";                                                                                                                          ",{}]]},"cursor":{"x":47}}],[0.232632,{"cursor":{"x":48}}],[0.335604,{"lines":{"4":[["localhost:~# while true; do; echo \"I'm bored!\"; e                                                                                                                        ",{}]]},"cursor":{"x":49}}],[0.18421,{"lines":{"4":[["localhost:~# while true; do; echo \"I'm bored!\"; en                                                                                                                       ",{}]]},"cursor":{"x":50}}],[0.096664,{"lines":{"4":[["localhost:~# while true; do; echo \"I'm bored!\"; end                                                                                                                      ",{}]]},"cursor":{"x":51}}],[0.457074,{"lines":{"4":[["localhost:~# while true; do; echo \"I'm bored!\"; end;                                                                                                                     ",{}]]},"cursor":{"x":52}}],[0.233535,{"cursor":{"x":0,"y":5}}],[0.006826,{"lines":{"5":[["bash: while: command not found                                                                                                                                           ",{}]],"6":[["bash: do: command not found                                                                                                                                              ",{}]]},"cursor":{"y":7}}],[0.04064,{}],[0.003404,{"lines":{"7":[["I'm bored!                                                                                                                                                               ",{}]],"8":[["bash: end: command not found                                                                                                                                             ",{}]],"9":[["localhost:~#                                                                                                                                                             ",{}]]},"cursor":{"x":13,"y":9}}],[1.328548,{}],[0.013532,{"lines":{"9":[["localhost:~# while true; do; echo \"I'm bored!\"; end;                                                                                                                     ",{}]]},"cursor":{"x":52}}],[0.424115,{"cursor":{"x":51}}],[0.000255,{"lines":{"9":[["localhost:~# while true; do; echo \"I'm bored!\"; end                                                                                                                      ",{}]]}}],[0.233156,{"lines":{"0":[["bash: end: command not found                                                                                                                                             ",{}]],"1":[["localhost:~# echo \"bored\"                                                                                                                                                ",{}]],"2":[["bored                                                                                                                                                                    ",{}]],"3":[["localhost:~# while true; do; echo \"I'm bored!\"; end;                                                                                                                     ",{}]],"4":[["bash: while: command not found                                                                                                                                           ",{}]],"5":[["bash: do: command not found                                                                                                                                              ",{}]],"6":[["I'm bored!                                                                                                                                                               ",{}]],"7":[["bash: end: command not found                                                                                                                                             ",{}]],"8":[["localhost:~# while true; do; echo \"I'm bored!\"; end                                                                                                                      ",{}]],"9":[["                                                                                                                                                                         ",{}]]},"cursor":{"x":0}}],[0.009965999999999999,{"lines":{"0":[["bash: while: command not found                                                                                                                                           ",{}]],"1":[["bash: do: command not found                                                                                                                                              ",{}]],"2":[["I'm bored!                                                                                                                                                               ",{}]],"3":[["bash: end: command not found                                                                                                                                             ",{}]],"4":[["localhost:~# while true; do; echo \"I'm bored!\"; end                                                                                                                      ",{}]],"5":[["bash: while: command not found                                                                                                                                           ",{}]],"6":[["bash: do: command not found                                                                                                                                              ",{}]],"7":[["I'm bored!                                                                                                                                                               ",{}]],"8":[["bash: end: command not found                                                                                                                                             ",{}]],"9":[["localhost:~#                                                                                                                                                             ",{}]]},"cursor":{"x":13}}],[3.002779,{"lines":{"9":[["localhost:~# c                                                                                                                                                           ",{}]]},"cursor":{"x":14}}],[1.121584,{"cursor":{"x":13}}],[0.000349,{"lines":{"9":[["localhost:~#                                                                                                                                                             ",{}]]}}],[0.5912269999999999,{"lines":{"9":[["localhost:~# h                                                                                                                                                           ",{}]]},"cursor":{"x":14}}],[0.265438,{"lines":{"9":[["localhost:~# hc                                                                                                                                                          ",{}]]},"cursor":{"x":15}}],[0.233182,{"cursor":{"x":14}}],[0.000417,{"lines":{"9":[["localhost:~# h                                                                                                                                                           ",{}]]}}],[0.191505,{"cursor":{"x":13}}],[0.000293,{"lines":{"9":[["localhost:~#                                                                                                                                                             ",{}]]}}],[0.240348,{"lines":{"9":[["localhost:~# b                                                                                                                                                           ",{}]]},"cursor":{"x":14}}],[0.136277,{"lines":{"9":[["localhost:~# ba                                                                                                                                                          ",{}]]},"cursor":{"x":15}}],[0.072516,{"lines":{"9":[["localhost:~# bas                                                                                                                                                         ",{}]]},"cursor":{"x":16}}],[0.166797,{"lines":{"9":[["localhost:~# bash                                                                                                                                                        ",{}]]},"cursor":{"x":17}}],[0.168815,{"lines":{"0":[["bash: do: command not found                                                                                                                                              ",{}]],"1":[["I'm bored!                                                                                                                                                               ",{}]],"2":[["bash: end: command not found                                                                                                                                             ",{}]],"3":[["localhost:~# while true; do; echo \"I'm bored!\"; end                                                                                                                      ",{}]],"4":[["bash: while: command not found                                                                                                                                           ",{}]],"5":[["bash: do: command not found                                                                                                                                              ",{}]],"6":[["I'm bored!                                                                                                                                                               ",{}]],"7":[["bash: end: command not found                                                                                                                                             ",{}]],"8":[["localhost:~# bash                                                                                                                                                        ",{}]],"9":[["                                                                                                                                                                         ",{}]]},"cursor":{"x":0}}],[0.002788,{"lines":{"9":[["localhost:~#                                                                                                                                                             ",{}]]},"cursor":{"x":13}}],[1.015448,{"lines":{"9":[["localhost:~# l                                                                                                                                                           ",{}]]},"cursor":{"x":14}}],[0.143742,{"lines":{"9":[["localhost:~# ls                                                                                                                                                          ",{}]]},"cursor":{"x":15}}],[0.121726,{"lines":{"0":[["I'm bored!                                                                                                                                                               ",{}]],"1":[["bash: end: command not found                                                                                                                                             ",{}]],"2":[["localhost:~# while true; do; echo \"I'm bored!\"; end                                                                                                                      ",{}]],"3":[["bash: while: command not found                                                                                                                                           ",{}]],"4":[["bash: do: command not found                                                                                                                                              ",{}]],"5":[["I'm bored!                                                                                                                                                               ",{}]],"6":[["bash: end: command not found                                                                                                                                             ",{}]],"7":[["localhost:~# bash                                                                                                                                                        ",{}]],"8":[["localhost:~# ls                                                                                                                                                          ",{}]],"9":[["                                                                                                                                                                         ",{}]]},"cursor":{"x":0}}],[0.002916,{"lines":{"9":[["localhost:~#                                                                                                                                                             ",{}]]},"cursor":{"x":13}}],[3.003253,{"lines":{"9":[["localhost:~# w                                                                                                                                                           ",{}]]},"cursor":{"x":14}}],[0.096847,{"lines":{"9":[["localhost:~# wh                                                                                                                                                          ",{}]]},"cursor":{"x":15}}],[0.07185999999999999,{"lines":{"9":[["localhost:~# whi                                                                                                                                                         ",{}]]},"cursor":{"x":16}}],[0.07199999999999999,{"lines":{"9":[["localhost:~# whil                                                                                                                                                        ",{}]]},"cursor":{"x":17}}],[0.047534,{"lines":{"9":[["localhost:~# while                                                                                                                                                       ",{}]]},"cursor":{"x":18}}],[0.16882,{"lines":{"0":[["bash: end: command not found                                                                                                                                             ",{}]],"1":[["localhost:~# while true; do; echo \"I'm bored!\"; end                                                                                                                      ",{}]],"2":[["bash: while: command not found                                                                                                                                           ",{}]],"3":[["bash: do: command not found                                                                                                                                              ",{}]],"4":[["I'm bored!                                                                                                                                                               ",{}]],"5":[["bash: end: command not found                                                                                                                                             ",{}]],"6":[["localhost:~# bash                                                                                                                                                        ",{}]],"7":[["localhost:~# ls                                                                                                                                                          ",{}]],"8":[["localhost:~# while                                                                                                                                                       ",{}]],"9":[["                                                                                                                                                                         ",{}]]},"cursor":{"x":0}}],[0.004029,{"lines":{"0":[["localhost:~# while true; do; echo \"I'm bored!\"; end                                                                                                                      ",{}]],"1":[["bash: while: command not found                                                                                                                                           ",{}]],"2":[["bash: do: command not found                                                                                                                                              ",{}]],"3":[["I'm bored!                                                                                                                                                               ",{}]],"4":[["bash: end: command not found                                                                                                                                             ",{}]],"5":[["localhost:~# bash                                                                                                                                                        ",{}]],"6":[["localhost:~# ls                                                                                                                                                          ",{}]],"7":[["localhost:~# while                                                                                                                                                       ",{}]],"8":[["bash: while: command not found                                                                                                                                           ",{}]],"9":[["localhost:~#                                                                                                                                                             ",{}]]},"cursor":{"x":13}}],[0.759083,{"lines":{"9":[["localhost:~# w                                                                                                                                                           ",{}]]},"cursor":{"x":14}}],[0.063697,{"lines":{"9":[["localhost:~# wh                                                                                                                                                          ",{}]]},"cursor":{"x":15}}],[0.120016,{"lines":{"9":[["localhost:~# whi                                                                                                                                                         ",{}]]},"cursor":{"x":16}}],[0.071682,{"lines":{"9":[["localhost:~# whil                                                                                                                                                        ",{}]]},"cursor":{"x":17}}],[0.071842,{"lines":{"9":[["localhost:~# while                                                                                                                                                       ",{}]]},"cursor":{"x":18}}],[0.144874,{"cursor":{"x":19}}],[0.107554,{"lines":{"9":[["localhost:~# while t                                                                                                                                                     ",{}]]},"cursor":{"x":20}}],[0.197501,{"lines":{"9":[["localhost:~# while tr                                                                                                                                                    ",{}]]},"cursor":{"x":21}}],[0.14435,{"lines":{"9":[["localhost:~# while tru                                                                                                                                                   ",{}]]},"cursor":{"x":22}}],[0.144601,{"lines":{"9":[["localhost:~# while true                                                                                                                                                  ",{}]]},"cursor":{"x":23}}],[0.73736,{"lines":{"9":[["localhost:~# while true;                                                                                                                                                 ",{}]]},"cursor":{"x":24}}],[0.8092510000000001,{"cursor":{"x":25}}],[3.003222,{"lines":{"9":[["localhost:~# while true; d                                                                                                                                               ",{}]]},"cursor":{"x":26}}],[0.047478,{"lines":{"9":[["localhost:~# while true; do                                                                                                                                              ",{}]]},"cursor":{"x":27}}],[0.166557,{"cursor":{"x":28}}],[0.593755,{"cursor":{"x":27}}],[0.000219,{}],[0.287956,{"lines":{"9":[["localhost:~# while true; do;                                                                                                                                             ",{}]]},"cursor":{"x":28}}],[0.206721,{"cursor":{"x":29}}],[0.860215,{"lines":{"9":[["localhost:~# while true; do; \"                                                                                                                                           ",{}]]},"cursor":{"x":30}}],[0.265431,{"lines":{"9":[["localhost:~# while true; do; \"e                                                                                                                                          ",{}]]},"cursor":{"x":31}}],[0.254238,{"lines":{"9":[["localhost:~# while true; do; \"ec                                                                                                                                         ",{}]]},"cursor":{"x":32}}],[0.096858,{"lines":{"9":[["localhost:~# while true; do; \"ech                                                                                                                                        ",{}]]},"cursor":{"x":33}}],[0.071966,{"lines":{"9":[["localhost:~# while true; do; \"echo                                                                                                                                       ",{}]]},"cursor":{"x":34}}],[0.21623,{"cursor":{"x":35}}],[0.328318,{"cursor":{"x":34}}],[0.000292,{}],[0.661552,{"cursor":{"x":33}}],[0.000275,{"lines":{"9":[["localhost:~# while true; do; \"ech                                                                                                                                        ",{}]]}}],[0.039281,{"cursor":{"x":32}}],[0.000454,{"lines":{"9":[["localhost:~# while true; do; \"ec                                                                                                                                         ",{}]]}}],[0.041505,{"cursor":{"x":31}}],[0.00033,{"lines":{"9":[["localhost:~# while true; do; \"e                                                                                                                                          ",{}]]}}],[0.04029,{"cursor":{"x":30}}],[0.000355,{"lines":{"9":[["localhost:~# while true; do; \"                                                                                                                                           ",{}]]}}],[0.194875,{"cursor":{"x":29}}],[0.000323,{"lines":{"9":[["localhost:~# while true; do;                                                                                                                                             ",{}]]}}],[0.59311,{"lines":{"9":[["localhost:~# while true; do; e                                                                                                                                           ",{}]]},"cursor":{"x":30}}],[0.240764,{"lines":{"9":[["localhost:~# while true; do; ec                                                                                                                                          ",{}]]},"cursor":{"x":31}}],[0.087259,{"lines":{"9":[["localhost:~# while true; do; ech                                                                                                                                         ",{}]]},"cursor":{"x":32}}],[0.10076,{"lines":{"9":[["localhost:~# while true; do; echo                                                                                                                                        ",{}]]},"cursor":{"x":33}}],[0.165362,{"cursor":{"x":34}}],[0.928392,{"lines":{"9":[["localhost:~# while true; do; echo \"                                                                                                                                      ",{}]]},"cursor":{"x":35}}],[0.39984,{"lines":{"9":[["localhost:~# while true; do; echo \"I                                                                                                                                     ",{}]]},"cursor":{"x":36}}],[0.640811,{"lines":{"9":[["localhost:~# while true; do; echo \"I'                                                                                                                                    ",{}]]},"cursor":{"x":37}}],[0.217931,{"lines":{"9":[["localhost:~# while true; do; echo \"I'm                                                                                                                                   ",{}]]},"cursor":{"x":38}}],[0.143932,{"cursor":{"x":39}}],[0.184313,{"lines":{"9":[["localhost:~# while true; do; echo \"I'm b                                                                                                                                 ",{}]]},"cursor":{"x":40}}],[0.07137,{"lines":{"9":[["localhost:~# while true; do; echo \"I'm bo                                                                                                                                ",{}]]},"cursor":{"x":41}}],[0.120139,{"lines":{"9":[["localhost:~# while true; do; echo \"I'm bor                                                                                                                               ",{}]]},"cursor":{"x":42}}],[0.07185999999999999,{"lines":{"9":[["localhost:~# while true; do; echo \"I'm bore                                                                                                                              ",{}]]},"cursor":{"x":43}}],[0.241391,{"lines":{"9":[["localhost:~# while true; do; echo \"I'm bored                                                                                                                             ",{}]]},"cursor":{"x":44}}],[0.377723,{"lines":{"9":[["localhost:~# while true; do; echo \"I'm bored.                                                                                                                            ",{}]]},"cursor":{"x":45}}],[0.335302,{"lines":{"9":[["localhost:~# while true; do; echo \"I'm bored.\"                                                                                                                           ",{}]]},"cursor":{"x":46}}],[0.82422,{"lines":{"9":[["localhost:~# while true; do; echo \"I'm bored.\";                                                                                                                          ",{}]]},"cursor":{"x":47}}],[3.003238,{"cursor":{"x":48}}],[0.232705,{"lines":{"9":[["localhost:~# while true; do; echo \"I'm bored.\"; d                                                                                                                        ",{}]]},"cursor":{"x":49}}],[0.119293,{"lines":{"9":[["localhost:~# while true; do; echo \"I'm bored.\"; do                                                                                                                       ",{}]]},"cursor":{"x":50}}],[0.096812,{"lines":{"9":[["localhost:~# while true; do; echo \"I'm bored.\"; don                                                                                                                      ",{}]]},"cursor":{"x":51}}],[0.143935,{"lines":{"9":[["localhost:~# while true; do; echo \"I'm bored.\"; done                                                                                                                     ",{}]]},"cursor":{"x":52}}],[0.144583,{"lines":{"0":[["bash: while: command not found                                                                                                                                           ",{}]],"1":[["bash: do: command not found                                                                                                                                              ",{}]],"2":[["I'm bored!                                                                                                                                                               ",{}]],"3":[["bash: end: command not found                                                                                                                                             ",{}]],"4":[["localhost:~# bash                                                                                                                                                        ",{}]],"5":[["localhost:~# ls                                                                                                                                                          ",{}]],"6":[["localhost:~# while                                                                                                                                                       ",{}]],"7":[["bash: while: command not found                                                                                                                                           ",{}]],"8":[["localhost:~# while true; do; echo \"I'm bored.\"; done                                                                                                                     ",{}]],"9":[["                                                                                                                                                                         ",{}]]},"cursor":{"x":0}}],[0.010957,{"lines":{"0":[["localhost:~# bash                                                                                                                                                        ",{}]],"1":[["localhost:~# ls                                                                                                                                                          ",{}]],"2":[["localhost:~# while                                                                                                                                                       ",{}]],"3":[["bash: while: command not found                                                                                                                                           ",{}]],"4":[["localhost:~# while true; do; echo \"I'm bored.\"; done                                                                                                                     ",{}]],"5":[["bash: while: command not found                                                                                                                                           ",{}]],"6":[["bash: do: command not found                                                                                                                                              ",{}]],"7":[["I'm bored.                                                                                                                                                               ",{}]],"8":[["bash: done: command not found                                                                                                                                            ",{}]],"9":[["localhost:~#                                                                                                                                                             ",{}]]},"cursor":{"x":13}}],[2.152555,{"lines":{"9":[["localhost:~# e                                                                                                                                                           ",{}]]},"cursor":{"x":14}}],[0.705742,{"cursor":{"x":13}}],[0.00032,{"lines":{"9":[["localhost:~#                                                                                                                                                             ",{}]]}}],[3.003208,{"lines":{"9":[["localhost:~# e                                                                                                                                                           ",{}]]},"cursor":{"x":14}}],[0.211941,{"lines":{"9":[["localhost:~# ec                                                                                                                                                          ",{}]]},"cursor":{"x":15}}],[0.070852,{"lines":{"9":[["localhost:~# ech                                                                                                                                                         ",{}]]},"cursor":{"x":16}}],[0.229274,{"lines":{"9":[["localhost:~# echo                                                                                                                                                        ",{}]]},"cursor":{"x":17}}],[0.000862,{"cursor":{"x":18}}],[0.308239,{"lines":{"9":[["localhost:~# echo $                                                                                                                                                      ",{}]]},"cursor":{"x":19}}],[0.477916,{"lines":{"9":[["localhost:~# echo $P                                                                                                                                                     ",{}]]},"cursor":{"x":20}}],[0.091029,{"lines":{"9":[["localhost:~# echo $PA                                                                                                                                                    ",{}]]},"cursor":{"x":21}}],[0.117243,{"lines":{"9":[["localhost:~# echo $PAT                                                                                                                                                   ",{}]]},"cursor":{"x":22}}],[0.120023,{"lines":{"9":[["localhost:~# echo $PATH                                                                                                                                                  ",{}]]},"cursor":{"x":23}}],[0.282285,{"lines":{"0":[["localhost:~# ls                                                                                                                                                          ",{}]],"1":[["localhost:~# while                                                                                                                                                       ",{}]],"2":[["bash: while: command not found                                                                                                                                           ",{}]],"3":[["localhost:~# while true; do; echo \"I'm bored.\"; done                                                                                                                     ",{}]],"4":[["bash: while: command not found                                                                                                                                           ",{}]],"5":[["bash: do: command not found                                                                                                                                              ",{}]],"6":[["I'm bored.                                                                                                                                                               ",{}]],"7":[["bash: done: command not found                                                                                                                                            ",{}]],"8":[["localhost:~# echo $PATH                                                                                                                                                  ",{}]],"9":[["                                                                                                                                                                         ",{}]]},"cursor":{"x":0}}],[0.004997000000000001,{"lines":{"0":[["localhost:~# while                                                                                                                                                       ",{}]],"1":[["bash: while: command not found                                                                                                                                           ",{}]],"2":[["localhost:~# while true; do; echo \"I'm bored.\"; done                                                                                                                     ",{}]],"3":[["bash: while: command not found                                                                                                                                           ",{}]],"4":[["bash: do: command not found                                                                                                                                              ",{}]],"5":[["I'm bored.                                                                                                                                                               ",{}]],"6":[["bash: done: command not found                                                                                                                                            ",{}]],"7":[["localhost:~# echo $PATH                                                                                                                                                  ",{}]],"8":[["$PATH                                                                                                                                                                    ",{}]],"9":[["localhost:~#                                                                                                                                                             ",{}]]},"cursor":{"x":13}}],[3.003236,{}],[0.002775,{"lines":{"0":[["Connection to server closed.                                                                                                                                             ",{}]],"1":[["localhost:~#                                                                                                                                                             ",{}]],"2":[["                                                                                                                                                                         ",{}]],"3":[["                                                                                                                                                                         ",{}]],"4":[["                                                                                                                                                                         ",{}]],"5":[["                                                                                                                                                                         ",{}]],"6":[["                                                                                                                                                                         ",{}]],"7":[["                                                                                                                                                                         ",{}]],"8":[["                                                                                                                                                                         ",{}]],"9":[["                                                                                                                                                                         ",{}]]},"cursor":{"y":1}}],[1.381249,{}],[0.002014,{}],[0.348253,{}],[0.002175,{}],[0.218035,{}],[0.001704,{}],[0.190854,{}],[0.001787,{}],[0.165354,{}],[0.003571,{}]]